{
	"alpha": {
		"start": 1,
		"end": 0.22
	},
	"scale": {
		"start": 0.25,
		"end": 0.75,
		"minimumScaleMultiplier": 0.5
	},
	"color": {
		"start": "ffffff",
		"end": "ffffff"
	},
	"speed": {
		"start": 200,
		"end": 50
	},
	"startRotation": {
		"min": 0,
		"max": 360
	},
	"rotationSpeed": {
		"min": 0,
		"max": 10
	},
	"lifetime": {
		"min": 4,
		"max": 4
	},
	"blendMode": "normal",
	"frequency": 0.016,
	"emitterLifetime": 0,
	"maxParticles": 500,
	"pos": {
		"x": 0,
		"y": 0
	},
	"addAtBack": false,
	"spawnType": "point"
}